scalenav/__init__.py
scalenav/data.py
scalenav/oop.py
scalenav/plotting.py
scalenav/rast_convert_par.py
scalenav/rast_converter.py
scalenav/scale_nav.py
scalenav/setup.py
scalenav/utils.py
scalenav/model/__init__.py
scalenav/model/classification.py
scalenav/model/functions.py
scalenav-0.0.6.data/data/test_data_0.parquet
scalenav-0.0.6.data/data/test_data_0.tif
scalenav-0.0.6.data/data/test_data_1.parquet
scalenav-0.0.6.data/data/test_data_1.tif
scalenav-0.0.6.data/data/test_data_2.parquet
scalenav-0.0.6.data/data/test_data_2.tif
scalenav-0.0.6.dist-info/entry_points.txt
scalenav-0.0.6.dist-info/licenses/LICENSE.txt
scalenav-0.0.6.dist-info/WHEEL
scalenav-0.0.6.dist-info/METADATA
scalenav-0.0.6.dist-info/RECORD
