Metadata-Version: 2.4
Name: scalenav
Version: 0.0.6
Summary: A package to project all sorts of data on the H3 grid and manipulate it at different spatial scales.
Keywords: hierarchical index,rescaling,geospatial
Author-email: Ivann Schlosser <ivann.schlosser@ouce.ox.ac.uk>
Maintainer-email: Ivann Schlosser <ivann.schlosser@ouce.ox.ac.uk>
Requires-Python: >=3.12
Classifier: Programming Language :: Python :: 3.12
Classifier: License :: OSI Approved :: MIT License
Classifier: Operating System :: OS Independent
License-File: LICENSE.txt
Requires-Dist: numpy
Requires-Dist: pandas
Requires-Dist: pyarrow
Requires-Dist: tqdm
Requires-Dist: pypalettes
Requires-Dist: rasterio
Requires-Dist: shapely
Requires-Dist: geopandas
Requires-Dist: h3==4.0.0b3
Project-URL: Documentation, https://nismod.github.io/scale-nav/
Project-URL: Homepage, https://github.com/nismod/scale-nav
Project-URL: Issues, https://github.com/nismod/scale-nav/issues
